[
    {
        "id": 1,
        "cover_img": "https://i.ibb.co/12tfp6f/library.jpg",
        "title": "How to get your first job as a self-taught programmer",
        "author": "arabic-man",
        "author_img": "https://i.ibb.co/jgyqDfn/soudi-arob-man111.jpg",
        "posted_date": "2024-03-12",
        "reading_time": 9,
        "hashtags": [
            "#beginners ",
            " #programming"
        ]
    },
    {
        "id": 2,
        "cover_img": "https://i.ibb.co/pZYhwB9/code.jpg",
        "title": "Enjoy your coding here make your web easy",
        "author": "Dubai-man",
        "author_img": "https://i.ibb.co/jgyqDfn/soudi-arob-man111.jpg",
        "posted_date": "2024-03-11",
        "reading_time": 7,
        "hashtags": [
            "#beginners ",
            " #programming"
        ]
    },
    {
        "id": 3,
        "cover_img": "https://i.ibb.co/YRVhF93/html-5.jpg",
        "title": "HTML is easy to learn - You will enjoy it!",
        "author": "Irani-man",
        "author_img": "https://i.ibb.co/jgyqDfn/soudi-arob-man111.jpg",
        "posted_date": "2024-03-10",
        "reading_time": 15,
        "hashtags": [
            "#beginners ",
            " #programming"
        ]
    },
    {
        "id": 4,
        "cover_img": "https://i.ibb.co/w7nzsvk/css3.webp",
        "title": " CSS is used for structuring,styling, and formatting web pages",
        "author": "Bangladeshi-man",
        "author_img": "https://i.ibb.co/jgyqDfn/soudi-arob-man111.jpg",
        "posted_date": "2024-03-09",
        "reading_time": 9,
        "hashtags": [
            "#beginners ",
            " #programming"
        ]
    },
    {
        "id": 5,
        "cover_img": "https://i.ibb.co/6n2fJmw/es6.jpg",
        "title": "ECMAScript was created to standardize JavaScript",
        "author": "Egypt-man",
        "author_img": "https://i.ibb.co/jgyqDfn/soudi-arob-man111.jpg",
        "posted_date": "2024-03-08",
        "reading_time": 5,
        "hashtags": [
            "#beginners   ",
            " #programming"
        ]
    }
]
